pyrebase/__init__.py
pyrebase/pyrebase.py
sseclient/__init__.py
sseclient/sseclient.py
totally_not_the_official_pyrebase-3.0.27.dist-info/METADATA
totally_not_the_official_pyrebase-3.0.27.dist-info/WHEEL
totally_not_the_official_pyrebase-3.0.27.dist-info/top_level.txt
totally_not_the_official_pyrebase-3.0.27.dist-info/RECORD
